kubling/__init__.py
kubling/dialect.py
kubling_sqlalchemy-25.1.dist-info/licenses/LICENSE
tests/__init__.py
tests/test_dialect.py
kubling_sqlalchemy-25.1.dist-info/METADATA
kubling_sqlalchemy-25.1.dist-info/WHEEL
kubling_sqlalchemy-25.1.dist-info/entry_points.txt
kubling_sqlalchemy-25.1.dist-info/top_level.txt
kubling_sqlalchemy-25.1.dist-info/RECORD
