Metadata-Version: 2.4
Name: kubling_sqlalchemy
Version: 25.1
Summary: SQLAlchemy dialect for Kubling
Home-page: https://github.com/kubling-community/kubling-sqlalchemy
License-File: LICENSE
Requires-Dist: sqlalchemy>=1.4
Requires-Dist: psycopg2-binary
Dynamic: description
Dynamic: description-content-type
Dynamic: home-page
Dynamic: license-file
Dynamic: requires-dist
Dynamic: summary
